{
  "id": "atlus",
  "platform": "pce",
  "category": "main_game",
  "titles": [
    {
      "text": "Atlus",
      "lang": "en",
      "script": "Latn",
      "region": "us",
      "form": "official",
      "source": "wikipedia_ja",
      "verified": false
    },
    {
      "text": "アトラス",
      "lang": "ja",
      "script": "Kana",
      "region": "jp",
      "form": "official",
      "source": "wikipedia_ja",
      "verified": true
    }
  ],
  "external_ids": {
    "wikidata": "Q780528"
  },
  "descriptions": [
    {
      "text": "Japanese video game company",
      "lang": "en",
      "source": "wikidata"
    },
    {
      "text": "studio japonais de développement de jeu vidéo",
      "lang": "fr",
      "source": "wikidata"
    },
    {
      "text": "japanischer Publisher für Computerspiele",
      "lang": "de",
      "source": "wikidata"
    },
    {
      "text": "日本の東京都品川区にあるゲーム会社",
      "lang": "ja",
      "source": "wikidata"
    },
    {
      "text": "Desarrolladora de videojuegos",
      "lang": "es",
      "source": "wikidata"
    },
    {
      "text": "azienda di videogiochi giapponese",
      "lang": "it",
      "source": "wikidata"
    },
    {
      "text": "일본의 비디오 게임 기업",
      "lang": "ko",
      "source": "wikidata"
    },
    {
      "text": "Atlus Co., Ltd. (株式会社アトラス, Kabushikigaisha Atorasu) is a Japanese video game developer, publisher, arcade manufacturer and distribution company based in Tokyo. A subsidiary of Sega, the company is known for the Megami Tensei, Persona, Etrian Odyssey, and Trauma Center series. Its corporate mascot is Jack Frost, a snowman-like character from its Megami Tensei series. The company is also known for its Print Club arcade machines, which are selfie photo sticker booths in East Asia.\nAtlus was established in April 1986 and spent its early years as a video game developer for other companies. It became a video game publisher of its own in 1989 and existed until it was merged into Index Corporation in October 2010. The Atlus name continued as a brand used by Index Corporation for video game publishing until it filed for bankruptcy in June 2013. This company was then acquired by Sega via its new subsidiary Sega Dream Corporation which renamed itself Index Corporation in November 2013. In April 2014, the non-video game assets and the Index name were spun off as a separate subsidiary of Sega, leaving the company with its video game division to be officially renamed Atlus.\nA North American bran",
      "lang": "en",
      "source": "wikipedia_en"
    }
  ]
}
