{
  "id": "puyo-puyo-cd",
  "platform": "pce",
  "category": "main_game",
  "titles": [
    {
      "text": "Puyo Puyo CD",
      "lang": "en",
      "script": "Latn",
      "region": "us",
      "form": "official",
      "source": "igdb",
      "verified": false
    },
    {
      "text": "ぷよぷよ CD",
      "lang": "ja",
      "script": "Hira",
      "region": "jp",
      "form": "official",
      "source": "igdb",
      "verified": false
    }
  ],
  "external_ids": {
    "igdb": 250339
  },
  "first_release_date": "1994-04-22",
  "media": [
    {
      "kind": "boxart",
      "url": "https://raw.githubusercontent.com/libretro-thumbnails/NEC_-_PC_Engine_CD_-_TurboGrafx-CD/master/Named_Boxarts/Puyo%20Puyo%20CD%20%28Japan%29.png",
      "source": "libretro_thumbnails"
    },
    {
      "kind": "titlescreen",
      "url": "https://raw.githubusercontent.com/libretro-thumbnails/NEC_-_PC_Engine_CD_-_TurboGrafx-CD/master/Named_Titles/Puyo%20Puyo%20CD%20%28Japan%29.png",
      "source": "libretro_thumbnails"
    },
    {
      "kind": "screenshot",
      "url": "https://raw.githubusercontent.com/libretro-thumbnails/NEC_-_PC_Engine_CD_-_TurboGrafx-CD/master/Named_Snaps/Puyo%20Puyo%20CD%20%28Japan%29.png",
      "source": "libretro_thumbnails"
    }
  ]
}
