{
  "id": "forsaken-64",
  "platform": "n64",
  "category": "main_game",
  "titles": [
    {
      "text": "Forsaken 64",
      "lang": "en",
      "script": "Latn",
      "form": "official",
      "source": "no_intro",
      "verified": false,
      "region": "us"
    }
  ],
  "roms": [
    {
      "name": "Forsaken 64 (USA)",
      "source": "no_intro",
      "region": "us",
      "serial": "NFOE",
      "size": 8388608,
      "crc32": "76c4333d",
      "md5": "5cdee5503a57d14533c66b35a5848899",
      "sha1": "7c670b224acfa960df902c866febb679806cb3fb"
    }
  ],
  "media": [
    {
      "kind": "boxart",
      "url": "https://raw.githubusercontent.com/libretro-thumbnails/Nintendo_-_Nintendo_64/master/Named_Boxarts/Forsaken%2064%20%28USA%29.png",
      "source": "libretro_thumbnails",
      "region": "us"
    },
    {
      "kind": "titlescreen",
      "url": "https://raw.githubusercontent.com/libretro-thumbnails/Nintendo_-_Nintendo_64/master/Named_Titles/Forsaken%2064%20%28USA%29.png",
      "source": "libretro_thumbnails",
      "region": "us"
    },
    {
      "kind": "screenshot",
      "url": "https://raw.githubusercontent.com/libretro-thumbnails/Nintendo_-_Nintendo_64/master/Named_Snaps/Forsaken%2064%20%28USA%29.png",
      "source": "libretro_thumbnails",
      "region": "us"
    }
  ]
}
