{
  "id": "eye-of-the-beholder",
  "platform": "md",
  "category": "main_game",
  "titles": [
    {
      "text": "アイ・オブ・ザ・ビホルダー",
      "lang": "ja",
      "script": "Kana",
      "region": "jp",
      "form": "official",
      "source": "wikidata",
      "verified": false
    },
    {
      "text": "Eye of the Beholder",
      "lang": "en",
      "script": "Latn",
      "region": "us",
      "form": "official",
      "source": "wikidata",
      "verified": false
    },
    {
      "text": "주시자의 눈",
      "lang": "ko",
      "script": "Hang",
      "region": "kr",
      "form": "official",
      "source": "wikidata",
      "verified": false
    },
    {
      "text": "魔眼杀机",
      "lang": "zh",
      "script": "Hans",
      "region": "cn",
      "form": "official",
      "source": "wikidata",
      "verified": false
    },
    {
      "text": "魔眼殺機",
      "lang": "zh",
      "script": "Hant",
      "region": "tw",
      "form": "official",
      "source": "wikidata",
      "verified": false
    },
    {
      "text": "Eye of the Beholder",
      "lang": "es",
      "script": "Latn",
      "region": "es",
      "form": "official",
      "source": "wikidata",
      "verified": false
    },
    {
      "text": "Eye of the Beholder",
      "lang": "fr",
      "script": "Latn",
      "region": "fr",
      "form": "official",
      "source": "wikidata",
      "verified": false
    },
    {
      "text": "Eye of the Beholder",
      "lang": "de",
      "script": "Latn",
      "region": "de",
      "form": "official",
      "source": "wikidata",
      "verified": false
    },
    {
      "text": "Eye of the Beholder",
      "lang": "it",
      "script": "Latn",
      "region": "it",
      "form": "official",
      "source": "wikidata",
      "verified": false
    }
  ],
  "first_release_date": "1990-01-01",
  "external_ids": {
    "wikidata": "Q1385731",
    "mobygames": 835
  },
  "descriptions": [
    {
      "text": "Computerspiel aus dem Jahr 1991",
      "lang": "de",
      "source": "wikidata"
    },
    {
      "text": "1991 video game",
      "lang": "en",
      "source": "wikidata"
    },
    {
      "text": "jeu vidéo de 1991",
      "lang": "fr",
      "source": "wikidata"
    },
    {
      "text": "videogioco del 1990",
      "lang": "it",
      "source": "wikidata"
    },
    {
      "text": "компьютерная игра 1990 года",
      "lang": "ru",
      "source": "wikidata"
    },
    {
      "text": "videojuego de 1990",
      "lang": "es",
      "source": "wikidata"
    },
    {
      "text": "jogo eletrônico de 1990",
      "lang": "pt",
      "source": "wikidata"
    },
    {
      "text": "1991년 롤플레잉 게임",
      "lang": "ko",
      "source": "wikidata"
    },
    {
      "text": "Eye of the Beholder is a role-playing video game for personal computers and video game consoles developed by Westwood Associates. It was published by Strategic Simulations, Inc. in 1991, for the MS-DOS operating system and later ported to the Amiga, the Sega CD and the Super NES. The Sega CD version features a soundtrack composed by Yuzo Koshiro and Motohiro Kawashima. A port to the Atari Lynx handheld was developed by NuFX in 1993, but was not released. In 2002, an adaptation of the same name was developed by Pronto Games for the Game Boy Advance.\nThe game has two sequels: the first was Eye of the Beholder II: The Legend of Darkmoon, which was also released in 1991; after Westwood Studios was acquired by Virgin Interactive in 1992, Eye of the Beholder III: Assault on Myth Drannor was released in 1993. The third game, however, was not developed by Westwood, who instead went on to create the Lands of Lore series.",
      "lang": "en",
      "source": "wikipedia_en"
    },
    {
      "text": "『アイ・オブ・ザ・ビホルダー』 (Eye of the Beholder) は、1991年にアメリカ合衆国のStrategic Simulations, Inc.から発売されたPC/AT互換機用ロールプレイングゲーム。\n主人公であるパーティ一向を操作し、大魔法使いケルベンのお告げによって発覚した都市の地下より迫りくる邪悪な存在を捜索する事を目的としている。ゲームシステムおよび世界設定はテーブルトークRPG『アドバンスト・ダンジョンズ&ドラゴンズ第2版』（1989年）をベースにしている。画面は3D形式で表示され、ゲーム中はリアルタイムで時間が進行していく他、戦闘以外にも様々な指示を与えられる自由度の高いシステムを特徴としている。\n開発はアメリカ合衆国のWestwood Studiosが行い、開発ディレクターはパソコン用ソフト『DragonStrike』（1990年）を手掛けたブルット・W・スペリー、プログラムはNES用ソフト『A Nightmare on Elm Street』（1989年）を手掛けたフィリップ・W・ゴロー、音楽はパソコン用ソフト『Mars Saga』（1988年）を手掛けたポール・S・ムードラが担当している。\n同年にAmigaに移植された他、日本ではポニーキャニオンによりPC-9800シリーズとメガCD、カプコンによりスーパーファミコンに移植された。メガCD版の音楽は『ベア・ナックルシリーズ』（1991年 - 1994年）の古代祐三・川島基宏が、効果音を崎元仁が担当している。元々のPC版がマウス操作を前提に作られているため、スーパーファミコン版はスーパーファミコン・マウスに、メガCD版はセガマウスにそれぞれ対応していた。\n後に続編となる『アイ・オブ・ザ・ビホルダーII ザ・レジェンド・オブ・ダークムーン』（1991年）、『アイ・オブ・ザ・ビホルダーIII アサルト・オン・ミス・ドラナー』（1993年）が発売された（後述）。また、日本国外では「DOS/V」版（英語版）の3部作を合わせたものがトリロジー版としてCD-ROMで発売されていた。",
      "lang": "ja",
      "source": "wikipedia_ja"
    },
    {
      "text": "아이 오브 더 비홀더(Eye of the Beholder)는 웨스트우드 스튜디오에서 개발한 개인용 컴퓨터 및 비디오 게임 콘솔용 롤플레잉 비디오 게임이다. 1991년 스트래직 시뮬레이션스에서 MS-DOS 운영 체제용으로 배급했으며 나중에 아미가, 세가 CD 및 슈퍼 패미컴(SNES)으로 포팅되었다. 세가 CD 버전에는 고시로 유조와 가와시마 모토히로가 작곡한 사운드 트랙이 포함되어 있다. 아타리 링크스 핸드헬드에 대한 포트는 1993년 NuFX에서 개발되었지만 출시되지 않았다. 2002년에는 프론토 게임스에서 게임보이 어드밴스용으로 같은 이름의 게임을 개발했다.\n이 게임에는 역시 1991년에 출시된 아이 오브 더 비홀더 II(Eye of the Beholder II: The Legend of Darkmoon)와 1993년에 출시된 아이 오브 더 비홀더 III(Eye of the Beholder III: Assault on Myth Drannor)라는 두 가지 속편이 있다. 그러나 세 번째 게임은 웨스트우드에서 개발하지 않았다. 1992년 버진 인터랙티브에 인수되어 대신 랜즈 오브 로어(Lands of Lore) 시리즈를 제작했다.",
      "lang": "ko",
      "source": "wikipedia_ko"
    },
    {
      "text": "《魔眼殺機》（英语：Eye of the Beholder）是Westwood Associates開發的電子角色扮演遊戲。遊戲1991年由Strategic Simulations在MS-DOS平台發行，之後移植到Amiga、Mega-CD、超級任天堂、PC-98等平台。\n《龍》為遊戲打出5/5分。",
      "lang": "zh",
      "source": "wikipedia_zh"
    },
    {
      "text": "Eye of the Beholder est un jeu vidéo de type dungeon crawler développé par Westwood Associates (futur Westwood Studios) et publié par Strategic Simulations, Inc. en 1991. Initialement sorti sur PC, le jeu a été adapté sur Amiga, Mega-CD, Super Nintendo et la console portable Lynx.",
      "lang": "fr",
      "source": "wikipedia_fr"
    },
    {
      "text": "Eye of the Beholder ist ein Computer-Rollenspiel von Westwood Associates und SSI aus dem Jahr 1991. Es basiert auf dem Rollenspiel-Regelwerk Advanced Dungeons & Dragons und erschien zunächst für DOS und Amiga, später auch PC-98, SNES und Mega-CD. Noch im selben Jahr wurde der Nachfolger Eye of the Beholder 2: Legende von Darkmoon veröffentlicht. 2002 brachte Pronto Games unter dem gleichen Titel ein Remake für die tragbare Konsole Game Boy Advance heraus.",
      "lang": "de",
      "source": "wikipedia_de"
    },
    {
      "text": "Eye of the Beholder è un videogioco di ruolo sviluppato dai Westwood Studios e pubblicato dalla Strategic Simulations, Inc. nel 1990 per i sistemi MS-DOS. In seguito il gioco è stato portato su sistemi Amiga, Sega CD e Super Nintendo. La versione per Sega CD era dotata di una colonna sonora esclusiva composta da Yuzo Koshiro.\nIl gioco ha avuto due seguiti: Eye of the Beholder II: The Legend of Darkmoon, pubblicato nel 1991 e Eye of the Beholder III: Assault on Myth Drannor del 1993. Il terzo titolo non è stato realizzato da Westwood. Esiste un ulteriore titolo per Game Boy Advance, intitolato semplicemente Eye of the Beholder ma tuttavia dissimile dai predecessori. \nLa struttura di base è simile a Dungeon Master, un videogioco presentato nel 1987 da FTL Games e ricordato come uno dei primi giochi del genere. Eye of the Beholder ha vinto numerosi premi per la storia, il gameplay e per gli enigmi.\nL'ambientazione è Forgotten Realms e il gioco si basa su Advanced Dungeons & Dragons 2ª edizione.",
      "lang": "it",
      "source": "wikipedia_it"
    },
    {
      "text": "Eye of the Beholder é um jogo eletrônico RPG para PC e consoles desenvolvido pela Westwood Associates . O jogo foi publicado pela Strategic Simulations, Inc. em 1991,\n para o sistema operacional MS-DOS e posteriormente portado para Amiga, Sega CD e SNES . A versão Sega CD traz trilha sonora composta por Yuzo Koshiro e Motohiro Kawashima . Umm porte para o portátil Atari Lynx foi desenvolvido pela NuFX em 1993, mas não foi lançado. Em 2002, uma adaptação de mesmo nome foi desenvolvida pela Pronto Games para o Game Boy Advance.\nO jogo tem duas sequências, Eye of the Beholder II: The Legend of Darkmoon, também lançado em 1991, e Eye of the Beholder III: Assault on Myth Drannor, lançado em 1993. O terceiro jogo, no entanto, não foi desenvolvido pela Westwood, que foi adquirida pela Virgin Interactive em 1992 e criou a série Lands of Lore .",
      "lang": "pt",
      "source": "wikipedia_pt"
    },
    {
      "text": "Eye of the Beholder — компьютерная ролевая игра производства Westwood Studios, основанная на ролевой системе Dungeons & Dragons. Является первой частью в серии компьютерных игр Eye of the Beholder.",
      "lang": "ru",
      "source": "wikipedia_ru"
    }
  ]
}
