{
  "id": "3x3-eyes-seima-kourin-den",
  "platform": "sfc",
  "category": "main_game",
  "titles": [
    {
      "text": "3x3 Eyes: Seima Kourin-den",
      "lang": "en",
      "script": "Latn",
      "region": "us",
      "form": "official",
      "source": "igdb",
      "verified": false
    },
    {
      "text": "3x3 Eyes 聖魔降臨伝",
      "lang": "ja",
      "script": "Jpan",
      "region": "jp",
      "form": "official",
      "source": "igdb",
      "verified": false
    },
    {
      "text": "3x3 Eyes: Seima Kourin-den",
      "lang": "ja",
      "script": "Latn",
      "region": "jp",
      "form": "romaji_transliteration",
      "source": "igdb",
      "verified": false
    }
  ],
  "external_ids": {
    "igdb": 15886
  },
  "first_release_date": "1992-07-28"
}
