{
  "id": "hokuto-no-ken-5-tenma-ryuusei-den-ai-zesshou",
  "platform": "sfc",
  "category": "main_game",
  "titles": [
    {
      "text": "Hokuto no Ken 5: Tenma Ryuusei-den Ai Zesshou",
      "lang": "en",
      "script": "Latn",
      "region": "us",
      "form": "official",
      "source": "igdb",
      "verified": false
    },
    {
      "text": "北斗の拳 5 天魔流星伝 哀 絶章",
      "lang": "ja",
      "script": "Jpan",
      "region": "jp",
      "form": "official",
      "source": "igdb",
      "verified": false
    }
  ],
  "external_ids": {
    "igdb": 42552
  },
  "first_release_date": "1992-07-10"
}
