{
  "id": "super-bomberman-panic-bomber-world",
  "platform": "sfc",
  "category": "main_game",
  "titles": [
    {
      "text": "Super Bomberman - Panic Bomber World",
      "lang": "en",
      "script": "Latn",
      "form": "official",
      "source": "no_intro",
      "verified": false,
      "region": "jp"
    },
    {
      "text": "ボンバーマン ぱにっくボンバーW ワールド",
      "lang": "ja",
      "script": "Jpan",
      "region": "jp",
      "form": "official",
      "source": "gamelist_ja",
      "verified": true
    }
  ],
  "roms": [
    {
      "name": "Super Bomberman - Panic Bomber World (Japan)",
      "source": "no_intro",
      "region": "jp",
      "size": 1048576,
      "crc32": "fc633ecb",
      "md5": "cc9c8195b55b94e075c771ca1628cbc8",
      "sha1": "3a8793c4e03f457d7cfc3c0ade6c67edf091f74b",
      "sha256": "404711c682df9b310f8da8555fe581688d0ceaa2397b82713ee92ae12636e96b"
    }
  ]
}
