{
  "id": "cyber-stadium-series-base-wars",
  "platform": "fc",
  "category": "main_game",
  "titles": [
    {
      "text": "Cyber Stadium Series - Base Wars",
      "lang": "en",
      "script": "Latn",
      "form": "official",
      "source": "no_intro",
      "verified": false,
      "region": "us"
    }
  ],
  "roms": [
    {
      "name": "Cyber Stadium Series - Base Wars (USA)",
      "source": "no_intro",
      "region": "us",
      "size": 262160,
      "crc32": "8b0bba89",
      "md5": "4af259949661e4f37eb15d3ed3d2f313",
      "sha1": "20cd6e0e64f1c91e453aec26bfd9461e1fc6587b",
      "sha256": "bd99383aa369ec4c5ce9f6cb4fdef2a1173496939905dd87cefa6abd65aa0cc4"
    }
  ],
  "media": [
    {
      "kind": "boxart",
      "url": "https://raw.githubusercontent.com/libretro-thumbnails/Nintendo_-_Nintendo_Entertainment_System/master/Named_Boxarts/Cyber%20Stadium%20Series%20-%20Base%20Wars%20%28USA%29.png",
      "source": "libretro_thumbnails",
      "region": "us"
    },
    {
      "kind": "titlescreen",
      "url": "https://raw.githubusercontent.com/libretro-thumbnails/Nintendo_-_Nintendo_Entertainment_System/master/Named_Titles/Cyber%20Stadium%20Series%20-%20Base%20Wars%20%28USA%29.png",
      "source": "libretro_thumbnails",
      "region": "us"
    },
    {
      "kind": "screenshot",
      "url": "https://raw.githubusercontent.com/libretro-thumbnails/Nintendo_-_Nintendo_Entertainment_System/master/Named_Snaps/Cyber%20Stadium%20Series%20-%20Base%20Wars%20%28USA%29.png",
      "source": "libretro_thumbnails",
      "region": "us"
    }
  ]
}
