{
  "id": "hoshi-wo-miru-hito-q5908008",
  "platform": "fc",
  "category": "main_game",
  "titles": [
    {
      "text": "星をみるひと",
      "lang": "ja",
      "script": "Jpan",
      "region": "jp",
      "form": "official",
      "source": "wikidata",
      "verified": false
    },
    {
      "text": "Hoshi wo Miru Hito",
      "lang": "en",
      "script": "Latn",
      "region": "us",
      "form": "official",
      "source": "wikidata",
      "verified": false
    }
  ],
  "first_release_date": "2020-07-30",
  "external_ids": {
    "wikidata": "Q5908008",
    "mobygames": 32112
  }
}
