{
  "id": "parasol-stars-rainbow-islands-ii",
  "platform": "fc",
  "category": "main_game",
  "titles": [
    {
      "text": "Parasol Stars - Rainbow Islands II",
      "lang": "en",
      "script": "Latn",
      "form": "official",
      "source": "no_intro",
      "verified": false,
      "region": "eu"
    }
  ],
  "roms": [
    {
      "name": "Parasol Stars - Rainbow Islands II (Europe)",
      "source": "no_intro",
      "region": "eu",
      "size": 262160,
      "crc32": "89bedaee",
      "md5": "b640f6769d34b6e1ece80a7af84e29ce",
      "sha1": "6dc4e3815493e1ec754f040f929cb4330a85940e",
      "sha256": "2000ef9d2ab5163768f49d2ea907b21c84c515af42b907b814b160323f191ca6"
    }
  ],
  "external_ids": {
    "igdb": 48278
  },
  "media": [
    {
      "kind": "boxart",
      "url": "https://raw.githubusercontent.com/libretro-thumbnails/Nintendo_-_Nintendo_Entertainment_System/master/Named_Boxarts/Parasol%20Stars%20-%20Rainbow%20Islands%20II%20%28Europe%29.png",
      "source": "libretro_thumbnails",
      "region": "eu"
    },
    {
      "kind": "titlescreen",
      "url": "https://raw.githubusercontent.com/libretro-thumbnails/Nintendo_-_Nintendo_Entertainment_System/master/Named_Titles/Parasol%20Stars%20-%20Rainbow%20Islands%20II%20%28Europe%29.png",
      "source": "libretro_thumbnails",
      "region": "eu"
    },
    {
      "kind": "screenshot",
      "url": "https://raw.githubusercontent.com/libretro-thumbnails/Nintendo_-_Nintendo_Entertainment_System/master/Named_Snaps/Parasol%20Stars%20-%20Rainbow%20Islands%20II%20%28Europe%29.png",
      "source": "libretro_thumbnails",
      "region": "eu"
    }
  ]
}
