{
  "id": "espn-x-games-skateboarding",
  "platform": "gba",
  "category": "main_game",
  "titles": [
    {
      "text": "ESPN X Games Skateboarding",
      "lang": "en",
      "script": "Latn",
      "region": "us",
      "form": "official",
      "source": "wikidata",
      "verified": false
    },
    {
      "text": "X-Games Skateboarding",
      "lang": "en",
      "script": "Latn",
      "region": "eu",
      "form": "official",
      "source": "igdb",
      "verified": true
    }
  ],
  "first_release_date": "2001-08-14",
  "external_ids": {
    "wikidata": "Q5324282",
    "mobygames": 39680,
    "igdb": 248752
  }
}
