{
  "id": "jurassic-park-iii-kyouryuu-ni-ainiikou",
  "platform": "gba",
  "category": "main_game",
  "titles": [
    {
      "text": "Jurassic Park III - Kyouryuu ni Ainiikou!",
      "lang": "en",
      "script": "Latn",
      "form": "official",
      "source": "no_intro",
      "verified": false,
      "region": "jp"
    },
    {
      "text": "ジュラシックパークIII 恐竜にあいにいこう！",
      "lang": "ja",
      "script": "Jpan",
      "region": "jp",
      "form": "official",
      "source": "romu",
      "verified": true
    }
  ],
  "roms": [
    {
      "name": "Jurassic Park III - Kyouryuu ni Ainiikou! (Japan)",
      "source": "no_intro",
      "region": "jp",
      "serial": "AJ3J",
      "size": 4194304,
      "crc32": "f2bf8990",
      "md5": "19371ad5f797b26c5e841992339ad37d",
      "sha1": "8c8115178caebcab3514601974682d3229ca06e6"
    }
  ],
  "descriptions": [
    {
      "text": "明らかに、元のパークを建設した人々は幾つかの見落としを犯していました。あなたはもっと上手くやれると思いますか？「ジュラシックパークIII：パークビルダー」で恐竜パークの創造と管理のすべての詳細を計画してみてください。最高レベルのストラテジーシミュレーションタイトルであるこのゲームでは、100種類の恐竜を管理し、配置し、健康を維持する責任があります。もちろん、レストランやショップ、アトラクション、ライドなどの問題もあります。あなたが作るパークが退屈すぎたり、手入れが行き届いていなかったり、高すぎたりすると、誰も訪れなくなるので、慎重な判断が求められます。パークの管理に加えて、パーク内のDNAストランドを集めて新しい恐竜を作り出し、人々を再び呼び戻す必要があります。これが手に負えないように思えますか？オープニングの日にあなたの先史時代の友達の一匹が逃げ出すまで待ってみてください。",
      "lang": "ja",
      "source": "romu"
    }
  ],
  "first_release_date": "2001-08-09",
  "media": [
    {
      "kind": "boxart",
      "url": "https://raw.githubusercontent.com/libretro-thumbnails/Nintendo_-_Game_Boy_Advance/master/Named_Boxarts/Jurassic%20Park%20III%20-%20Kyouryuu%20ni%20Ainiikou%21%20%28Japan%29.png",
      "source": "libretro_thumbnails",
      "region": "jp"
    },
    {
      "kind": "titlescreen",
      "url": "https://raw.githubusercontent.com/libretro-thumbnails/Nintendo_-_Game_Boy_Advance/master/Named_Titles/Jurassic%20Park%20III%20-%20Kyouryuu%20ni%20Ainiikou%21%20%28Japan%29.png",
      "source": "libretro_thumbnails",
      "region": "jp"
    },
    {
      "kind": "screenshot",
      "url": "https://raw.githubusercontent.com/libretro-thumbnails/Nintendo_-_Game_Boy_Advance/master/Named_Snaps/Jurassic%20Park%20III%20-%20Kyouryuu%20ni%20Ainiikou%21%20%28Japan%29.png",
      "source": "libretro_thumbnails",
      "region": "jp"
    }
  ]
}
