{
  "id": "monster-rancher-advance-2",
  "platform": "gba",
  "category": "main_game",
  "titles": [
    {
      "text": "モンスターファームアドバンス2",
      "lang": "ja",
      "script": "Kana",
      "region": "jp",
      "form": "official",
      "source": "wikidata",
      "verified": true
    },
    {
      "text": "Monster Rancher Advance 2",
      "lang": "en",
      "script": "Latn",
      "region": "us",
      "form": "official",
      "source": "wikidata",
      "verified": false
    },
    {
      "text": "Monster Rancher Advance 2",
      "lang": "fr",
      "script": "Latn",
      "region": "fr",
      "form": "official",
      "source": "wikidata",
      "verified": false
    }
  ],
  "first_release_date": "2002-10-25",
  "external_ids": {
    "wikidata": "Q6902814",
    "mobygames": 12001,
    "igdb": 6512
  },
  "roms": [
    {
      "name": "Monster Rancher Advance 2 (USA)",
      "source": "no_intro",
      "region": "us",
      "serial": "A2QE",
      "size": 8388608,
      "crc32": "1d695b1b",
      "md5": "c92823ec801e976852b67ac3f10723a7",
      "sha1": "2a67770024d4e292e6fa30a9c2ae40d671f2e8ea"
    }
  ],
  "media": [
    {
      "kind": "boxart",
      "url": "https://raw.githubusercontent.com/libretro-thumbnails/Nintendo_-_Game_Boy_Advance/master/Named_Boxarts/Monster%20Rancher%20Advance%202%20%28USA%29.png",
      "source": "libretro_thumbnails",
      "region": "us"
    },
    {
      "kind": "titlescreen",
      "url": "https://raw.githubusercontent.com/libretro-thumbnails/Nintendo_-_Game_Boy_Advance/master/Named_Titles/Monster%20Rancher%20Advance%202%20%28USA%29.png",
      "source": "libretro_thumbnails",
      "region": "us"
    },
    {
      "kind": "screenshot",
      "url": "https://raw.githubusercontent.com/libretro-thumbnails/Nintendo_-_Game_Boy_Advance/master/Named_Snaps/Monster%20Rancher%20Advance%202%20%28USA%29.png",
      "source": "libretro_thumbnails",
      "region": "us"
    }
  ],
  "descriptions": [
    {
      "text": "Computerspiel aus dem Jahr 2002",
      "lang": "de",
      "source": "wikidata"
    },
    {
      "text": "2002 video game",
      "lang": "en",
      "source": "wikidata"
    },
    {
      "text": "videojuego de 2002",
      "lang": "es",
      "source": "wikidata"
    },
    {
      "text": "jeu vidéo de 2002",
      "lang": "fr",
      "source": "wikidata"
    },
    {
      "text": "videogioco del 2002",
      "lang": "it",
      "source": "wikidata"
    },
    {
      "text": "компьютерная игра 2002 года",
      "lang": "ru",
      "source": "wikidata"
    },
    {
      "text": "videojogo de 2002",
      "lang": "pt",
      "source": "wikidata"
    },
    {
      "text": "Monster Rancher Advance 2 (known in Japan as Monster Farm Advance 2 (モンスターファーム アドバンス 2, Monsutā Fāmu Adobansu Tsū)) is the second of the Monster Rancher games to be released on Game Boy Advance. It is the sequel to Monster Rancher Advance.",
      "lang": "en",
      "source": "wikipedia_en"
    },
    {
      "text": "『モンスターファームアドバンス2』はテクモが2002年10月25日にゲームボーイアドバンス用ソフトとして発売した。",
      "lang": "ja",
      "source": "wikipedia_ja"
    },
    {
      "text": "Monster Rancher Advance 2, aussi connu sous le nom de Monster Farm Advance 2 (モンスターファーム アドバンス 2, Monsutā Fāmu Adobansu 2) au Japon, est un jeu vidéo Game Boy Advance issu de la série de jeux vidéo Monster Rancher , publié en 2002.",
      "lang": "fr",
      "source": "wikipedia_fr"
    }
  ]
}
