{
  "id": "daisenryaku-ds-great-strategy",
  "platform": "nds",
  "category": "main_game",
  "titles": [
    {
      "text": "Daisenryaku DS - Great Strategy",
      "lang": "en",
      "script": "Latn",
      "form": "official",
      "source": "no_intro",
      "verified": false,
      "region": "jp"
    }
  ],
  "roms": [
    {
      "name": "Daisenryaku DS - Great Strategy (Japan)",
      "source": "no_intro",
      "region": "jp",
      "serial": "ASRJ",
      "size": 67108864,
      "crc32": "899b5bfc",
      "md5": "2f756d1dd4be43de622ad8bfaea5a62a",
      "sha1": "08bf743d7b1cdfe029218a872e0c3a22edce6cd3"
    }
  ],
  "media": [
    {
      "kind": "boxart",
      "url": "https://raw.githubusercontent.com/libretro-thumbnails/Nintendo_-_Nintendo_DS/master/Named_Boxarts/Daisenryaku%20DS%20-%20Great%20Strategy%20%28Japan%29.png",
      "source": "libretro_thumbnails",
      "region": "jp"
    },
    {
      "kind": "titlescreen",
      "url": "https://raw.githubusercontent.com/libretro-thumbnails/Nintendo_-_Nintendo_DS/master/Named_Titles/Daisenryaku%20DS%20-%20Great%20Strategy%20%28Japan%29.png",
      "source": "libretro_thumbnails",
      "region": "jp"
    },
    {
      "kind": "screenshot",
      "url": "https://raw.githubusercontent.com/libretro-thumbnails/Nintendo_-_Nintendo_DS/master/Named_Snaps/Daisenryaku%20DS%20-%20Great%20Strategy%20%28Japan%29.png",
      "source": "libretro_thumbnails",
      "region": "jp"
    }
  ]
}
