{
  "id": "inazuma-eleven-2-kyoui-no-shinryakusha-fire",
  "platform": "nds",
  "category": "main_game",
  "titles": [
    {
      "text": "Inazuma Eleven 2 - Kyoui no Shinryakusha - Fire",
      "lang": "en",
      "script": "Latn",
      "form": "official",
      "source": "no_intro",
      "verified": false,
      "region": "jp"
    }
  ],
  "roms": [
    {
      "name": "Inazuma Eleven 2 - Kyoui no Shinryakusha - Fire (Japan)",
      "source": "no_intro",
      "region": "jp",
      "serial": "BEEJ",
      "size": 268435456,
      "crc32": "510248c4",
      "md5": "5c38397b3f3e1e1621a0b54cf37cc503",
      "sha1": "7855b8ff20d172421ea5f37cbf1ce35b088932bf",
      "sha256": "9935547e421555e7756afddea4915c7d16cc0f990f6fe30719e55e47d0f51136"
    },
    {
      "name": "Inazuma Eleven 2 - Kyoui no Shinryakusha - Fire (Japan) (Rev 1)",
      "source": "no_intro",
      "region": "jp",
      "serial": "BEEJ",
      "size": 268435456,
      "crc32": "f62938af",
      "md5": "1d5b3de31be1d7c04aac3424d0c6e8f4",
      "sha1": "b7a58fbe8b699b99064f5989ac3cbd41bd3fdbc7"
    }
  ],
  "media": [
    {
      "kind": "boxart",
      "url": "https://raw.githubusercontent.com/libretro-thumbnails/Nintendo_-_Nintendo_DS/master/Named_Boxarts/Inazuma%20Eleven%202%20-%20Kyoui%20no%20Shinryakusha%20-%20Fire%20%28Japan%29.png",
      "source": "libretro_thumbnails",
      "region": "jp"
    },
    {
      "kind": "screenshot",
      "url": "https://raw.githubusercontent.com/libretro-thumbnails/Nintendo_-_Nintendo_DS/master/Named_Snaps/Inazuma%20Eleven%202%20-%20Kyoui%20no%20Shinryakusha%20-%20Fire%20%28Japan%29.png",
      "source": "libretro_thumbnails",
      "region": "jp"
    },
    {
      "kind": "boxart",
      "url": "https://raw.githubusercontent.com/libretro-thumbnails/Nintendo_-_Nintendo_DS/master/Named_Boxarts/Inazuma%20Eleven%202%20-%20Kyoui%20no%20Shinryakusha%20-%20Fire%20%28Japan%29%20%28Rev%201%29.png",
      "source": "libretro_thumbnails",
      "region": "jp"
    },
    {
      "kind": "screenshot",
      "url": "https://raw.githubusercontent.com/libretro-thumbnails/Nintendo_-_Nintendo_DS/master/Named_Snaps/Inazuma%20Eleven%202%20-%20Kyoui%20no%20Shinryakusha%20-%20Fire%20%28Japan%29%20%28Rev%201%29.png",
      "source": "libretro_thumbnails",
      "region": "jp"
    }
  ]
}
