{
  "id": "isanghan-naraui-princess",
  "platform": "nds",
  "category": "main_game",
  "titles": [
    {
      "text": "Isanghan Naraui Princess",
      "lang": "en",
      "script": "Latn",
      "form": "official",
      "source": "no_intro",
      "verified": false
    }
  ],
  "roms": [
    {
      "name": "Isanghan Naraui Princess (Korea)",
      "source": "no_intro",
      "region": "kr",
      "serial": "YROK",
      "size": 33554432,
      "crc32": "43dfdf69",
      "md5": "57c6b9d7936239c5b0ab3db09a379ce3",
      "sha1": "579e2c82950c666c7b98d9d4d9b5229bc8f8cd07"
    }
  ],
  "media": [
    {
      "kind": "boxart",
      "url": "https://raw.githubusercontent.com/libretro-thumbnails/Nintendo_-_Nintendo_DS/master/Named_Boxarts/Isanghan%20Naraui%20Princess%20%28Korea%29.png",
      "source": "libretro_thumbnails",
      "region": "kr"
    },
    {
      "kind": "titlescreen",
      "url": "https://raw.githubusercontent.com/libretro-thumbnails/Nintendo_-_Nintendo_DS/master/Named_Titles/Isanghan%20Naraui%20Princess%20%28Korea%29.png",
      "source": "libretro_thumbnails",
      "region": "kr"
    },
    {
      "kind": "screenshot",
      "url": "https://raw.githubusercontent.com/libretro-thumbnails/Nintendo_-_Nintendo_DS/master/Named_Snaps/Isanghan%20Naraui%20Princess%20%28Korea%29.png",
      "source": "libretro_thumbnails",
      "region": "kr"
    }
  ]
}
