{
  "id": "katekyoo-hitman-reborn-ds-flame-rumble-kaien-ring-soudatsusen",
  "platform": "nds",
  "category": "main_game",
  "titles": [
    {
      "text": "Katekyoo Hitman Reborn! DS - Flame Rumble - Kaien Ring Soudatsusen!",
      "lang": "en",
      "script": "Latn",
      "form": "official",
      "source": "no_intro",
      "verified": false,
      "region": "jp"
    }
  ],
  "roms": [
    {
      "name": "Katekyoo Hitman Reborn! DS - Flame Rumble - Kaien Ring Soudatsusen! (Japan)",
      "source": "no_intro",
      "region": "jp",
      "serial": "YH4J",
      "size": 67108864,
      "crc32": "42ebb671",
      "md5": "0fe8ace301e0714d0968f1d2886c5e8b",
      "sha1": "25394a750e7c10cf7b9656fd1eff3ff780cb075c",
      "sha256": "ee8408ceaf4bb99db9bd6ab0b707a6959bddd423ca02806b23526d47d1c3f113"
    }
  ],
  "media": [
    {
      "kind": "boxart",
      "url": "https://raw.githubusercontent.com/libretro-thumbnails/Nintendo_-_Nintendo_DS/master/Named_Boxarts/Katekyoo%20Hitman%20Reborn%21%20DS%20-%20Flame%20Rumble%20-%20Kaien%20Ring%20Soudatsusen%21%20%28Japan%29.png",
      "source": "libretro_thumbnails",
      "region": "jp"
    },
    {
      "kind": "screenshot",
      "url": "https://raw.githubusercontent.com/libretro-thumbnails/Nintendo_-_Nintendo_DS/master/Named_Snaps/Katekyoo%20Hitman%20Reborn%21%20DS%20-%20Flame%20Rumble%20-%20Kaien%20Ring%20Soudatsusen%21%20%28Japan%29.png",
      "source": "libretro_thumbnails",
      "region": "jp"
    }
  ]
}
