{
  "id": "layton-gyosuwa-angmaui-sangja",
  "platform": "nds",
  "category": "main_game",
  "titles": [
    {
      "text": "Layton Gyosuwa Angmaui Sangja",
      "lang": "en",
      "script": "Latn",
      "form": "official",
      "source": "no_intro",
      "verified": false
    }
  ],
  "roms": [
    {
      "name": "Layton Gyosuwa Angmaui Sangja (Korea)",
      "source": "no_intro",
      "region": "kr",
      "serial": "YLTK",
      "size": 134217728,
      "crc32": "dc3359e6",
      "md5": "b6a82af99ea272dfcb6685c145aa2e78",
      "sha1": "694b359dc8a942f30c4af0e1deaa740fcb594db2",
      "sha256": "6b24b273491b335da27c71aac14e7d6fa109f365b03d576db38427c44d3675c2"
    }
  ]
}
