{
  "id": "maji-de-manabu-lec-de-ukaru-ds-kikenbutsu-toriatsukaisha-otsushu-4-rui",
  "platform": "nds",
  "category": "main_game",
  "titles": [
    {
      "text": "Maji de Manabu - LEC de Ukaru - DS Kikenbutsu Toriatsukaisha Otsushu 4 Rui",
      "lang": "en",
      "script": "Latn",
      "form": "official",
      "source": "no_intro",
      "verified": false,
      "region": "jp"
    }
  ],
  "roms": [
    {
      "name": "Maji de Manabu - LEC de Ukaru - DS Kikenbutsu Toriatsukaisha Otsushu 4 Rui (Japan) (Rev 1)",
      "source": "no_intro",
      "region": "jp",
      "serial": "BK4J",
      "size": 134217728,
      "crc32": "c0db451a",
      "md5": "a00fbf10a8e0c8190ed487a3e6159d8f",
      "sha1": "87049ddbd8a3096462e0e18209c2bb1daec597f9"
    },
    {
      "name": "Maji de Manabu - LEC de Ukaru - DS Kikenbutsu Toriatsukaisha Otsushu 4 Rui (Japan)",
      "source": "no_intro",
      "region": "jp",
      "serial": "BK4J",
      "size": 134217728,
      "crc32": "ed4d434d",
      "md5": "31c182333b8a48b82aa48458ed40fca1",
      "sha1": "103597704d12cf63a254bb8a19b7c59fce821618"
    }
  ],
  "media": [
    {
      "kind": "boxart",
      "url": "https://raw.githubusercontent.com/libretro-thumbnails/Nintendo_-_Nintendo_DS/master/Named_Boxarts/Maji%20de%20Manabu%20-%20LEC%20de%20Ukaru%20-%20DS%20Kikenbutsu%20Toriatsukaisha%20Otsushu%204%20Rui%20%28Japan%29%20%28Rev%201%29.png",
      "source": "libretro_thumbnails",
      "region": "jp"
    },
    {
      "kind": "titlescreen",
      "url": "https://raw.githubusercontent.com/libretro-thumbnails/Nintendo_-_Nintendo_DS/master/Named_Titles/Maji%20de%20Manabu%20-%20LEC%20de%20Ukaru%20-%20DS%20Kikenbutsu%20Toriatsukaisha%20Otsushu%204%20Rui%20%28Japan%29%20%28Rev%201%29.png",
      "source": "libretro_thumbnails",
      "region": "jp"
    },
    {
      "kind": "screenshot",
      "url": "https://raw.githubusercontent.com/libretro-thumbnails/Nintendo_-_Nintendo_DS/master/Named_Snaps/Maji%20de%20Manabu%20-%20LEC%20de%20Ukaru%20-%20DS%20Kikenbutsu%20Toriatsukaisha%20Otsushu%204%20Rui%20%28Japan%29%20%28Rev%201%29.png",
      "source": "libretro_thumbnails",
      "region": "jp"
    },
    {
      "kind": "boxart",
      "url": "https://raw.githubusercontent.com/libretro-thumbnails/Nintendo_-_Nintendo_DS/master/Named_Boxarts/Maji%20de%20Manabu%20-%20LEC%20de%20Ukaru%20-%20DS%20Kikenbutsu%20Toriatsukaisha%20Otsushu%204%20Rui%20%28Japan%29.png",
      "source": "libretro_thumbnails",
      "region": "jp"
    },
    {
      "kind": "titlescreen",
      "url": "https://raw.githubusercontent.com/libretro-thumbnails/Nintendo_-_Nintendo_DS/master/Named_Titles/Maji%20de%20Manabu%20-%20LEC%20de%20Ukaru%20-%20DS%20Kikenbutsu%20Toriatsukaisha%20Otsushu%204%20Rui%20%28Japan%29.png",
      "source": "libretro_thumbnails",
      "region": "jp"
    },
    {
      "kind": "screenshot",
      "url": "https://raw.githubusercontent.com/libretro-thumbnails/Nintendo_-_Nintendo_DS/master/Named_Snaps/Maji%20de%20Manabu%20-%20LEC%20de%20Ukaru%20-%20DS%20Kikenbutsu%20Toriatsukaisha%20Otsushu%204%20Rui%20%28Japan%29.png",
      "source": "libretro_thumbnails",
      "region": "jp"
    }
  ]
}
