{
  "id": "petz-dogz-fashion",
  "platform": "nds",
  "category": "main_game",
  "titles": [
    {
      "text": "Petz - Dogz Fashion",
      "lang": "en",
      "script": "Latn",
      "form": "official",
      "source": "no_intro",
      "verified": false,
      "region": "us"
    }
  ],
  "roms": [
    {
      "name": "Petz - Dogz Fashion (USA) (En,Fr,Es) (Rev 1)",
      "source": "no_intro",
      "region": "us",
      "serial": "YNZE",
      "size": 67108864,
      "crc32": "f3db0c1b",
      "md5": "e03687bf52fddffd8da97432a2f124d0",
      "sha1": "ba971de95fa3e863580b531c08276aaeb65e4c2d"
    },
    {
      "name": "Petz - Dogz Fashion (USA)",
      "source": "no_intro",
      "region": "us",
      "serial": "YNZE",
      "size": 67108864,
      "crc32": "3f89245f",
      "md5": "adab2fa181ca75461ea18e74a921f286",
      "sha1": "0195e1cf4bd571428a8e076b89567ce38ba1cb38"
    }
  ],
  "external_ids": {
    "igdb": 123373
  },
  "media": [
    {
      "kind": "boxart",
      "url": "https://raw.githubusercontent.com/libretro-thumbnails/Nintendo_-_Nintendo_DS/master/Named_Boxarts/Petz%20-%20Dogz%20Fashion%20%28USA%29%20%28En%2CFr%2CEs%29%20%28Rev%201%29.png",
      "source": "libretro_thumbnails",
      "region": "us"
    },
    {
      "kind": "titlescreen",
      "url": "https://raw.githubusercontent.com/libretro-thumbnails/Nintendo_-_Nintendo_DS/master/Named_Titles/Petz%20-%20Dogz%20Fashion%20%28USA%29%20%28En%2CFr%2CEs%29%20%28Rev%201%29.png",
      "source": "libretro_thumbnails",
      "region": "us"
    },
    {
      "kind": "screenshot",
      "url": "https://raw.githubusercontent.com/libretro-thumbnails/Nintendo_-_Nintendo_DS/master/Named_Snaps/Petz%20-%20Dogz%20Fashion%20%28USA%29%20%28En%2CFr%2CEs%29%20%28Rev%201%29.png",
      "source": "libretro_thumbnails",
      "region": "us"
    },
    {
      "kind": "boxart",
      "url": "https://raw.githubusercontent.com/libretro-thumbnails/Nintendo_-_Nintendo_DS/master/Named_Boxarts/Petz%20-%20Dogz%20Fashion%20%28USA%29.png",
      "source": "libretro_thumbnails",
      "region": "us"
    },
    {
      "kind": "titlescreen",
      "url": "https://raw.githubusercontent.com/libretro-thumbnails/Nintendo_-_Nintendo_DS/master/Named_Titles/Petz%20-%20Dogz%20Fashion%20%28USA%29.png",
      "source": "libretro_thumbnails",
      "region": "us"
    },
    {
      "kind": "screenshot",
      "url": "https://raw.githubusercontent.com/libretro-thumbnails/Nintendo_-_Nintendo_DS/master/Named_Snaps/Petz%20-%20Dogz%20Fashion%20%28USA%29.png",
      "source": "libretro_thumbnails",
      "region": "us"
    }
  ]
}
