{
  "id": "rune-factory-sinmokjjangiyagi",
  "platform": "nds",
  "category": "main_game",
  "titles": [
    {
      "text": "Rune Factory - Sinmokjjangiyagi",
      "lang": "en",
      "script": "Latn",
      "form": "official",
      "source": "no_intro",
      "verified": false
    }
  ],
  "roms": [
    {
      "name": "Rune Factory - Sinmokjjangiyagi (Korea)",
      "source": "no_intro",
      "region": "kr",
      "serial": "ARFK",
      "size": 134217728,
      "crc32": "19fba62c",
      "md5": "fe08ce65df47d2adab77ae6c9f03f953",
      "sha1": "90da9ecd5170482a2ab74d71ea0d5a8af7de4338",
      "sha256": "130385689b7fafb7de79d54f742fb6fe05b3a8fe12db14fc94238c779dd0d414"
    }
  ]
}
