{
  "id": "sakashou-ds",
  "platform": "nds",
  "category": "main_game",
  "titles": [
    {
      "text": "Sakashou DS",
      "lang": "en",
      "script": "Latn",
      "form": "official",
      "source": "no_intro",
      "verified": false,
      "region": "jp"
    }
  ],
  "roms": [
    {
      "name": "Sakashou DS (Japan)",
      "source": "no_intro",
      "region": "jp",
      "serial": "A5BJ",
      "size": 67108864,
      "crc32": "c4bb986d",
      "md5": "3c346501c807add8742c6abb6030ecdb",
      "sha1": "88275040745b97071889cbb13760495016550658"
    }
  ],
  "media": [
    {
      "kind": "boxart",
      "url": "https://raw.githubusercontent.com/libretro-thumbnails/Nintendo_-_Nintendo_DS/master/Named_Boxarts/Sakashou%20DS%20%28Japan%29.png",
      "source": "libretro_thumbnails",
      "region": "jp"
    },
    {
      "kind": "screenshot",
      "url": "https://raw.githubusercontent.com/libretro-thumbnails/Nintendo_-_Nintendo_DS/master/Named_Snaps/Sakashou%20DS%20%28Japan%29.png",
      "source": "libretro_thumbnails",
      "region": "jp"
    }
  ]
}
