{
  "id": "spider-man-web-of-shadows-q2635988",
  "platform": "nds",
  "category": "main_game",
  "titles": [
    {
      "text": "スパイダーマン：ウェブ・オブ・シャドウズ",
      "lang": "ja",
      "script": "Kana",
      "region": "jp",
      "form": "official",
      "source": "wikidata",
      "verified": false
    },
    {
      "text": "Spider-Man: Web of Shadows",
      "lang": "en",
      "script": "Latn",
      "region": "us",
      "form": "official",
      "source": "wikidata",
      "verified": false
    }
  ],
  "first_release_date": "2008-10-21",
  "external_ids": {
    "wikidata": "Q2635988",
    "mobygames": 37156
  }
}
