{
  "id": "the-chronicles-of-narnia-prince-caspian",
  "platform": "nds",
  "category": "main_game",
  "titles": [
    {
      "text": "ナルニア国物語/第2章: カスピアン王子の角笛",
      "lang": "ja",
      "script": "Jpan",
      "region": "jp",
      "form": "official",
      "source": "wikidata",
      "verified": false
    },
    {
      "text": "The Chronicles of Narnia: Prince Caspian",
      "lang": "en",
      "script": "Latn",
      "region": "us",
      "form": "official",
      "source": "wikidata",
      "verified": false
    }
  ],
  "first_release_date": "2008-05-15",
  "external_ids": {
    "wikidata": "Q2025168",
    "mobygames": 36158
  }
}
