{
  "id": "what-s-cooking-jamie-oliver",
  "platform": "nds",
  "category": "main_game",
  "titles": [
    {
      "text": "What's Cooking - Jamie Oliver",
      "lang": "en",
      "script": "Latn",
      "form": "official",
      "source": "no_intro",
      "verified": false,
      "region": "us"
    }
  ],
  "roms": [
    {
      "name": "What's Cooking - Jamie Oliver (USA) (En,Fr,Es)",
      "source": "no_intro",
      "region": "us",
      "serial": "YCVE",
      "size": 16777216,
      "crc32": "6705cf4e",
      "md5": "04f4a8ae5a6ddcc7e481e83d5f5bdb86",
      "sha1": "cb4591a4735a67a5cfd5a8fb4bb3c8fa37660720"
    },
    {
      "name": "What's Cooking - Jamie Oliver (Europe) (En,Fr,De,Es,It)",
      "source": "no_intro",
      "region": "eu",
      "serial": "YCVP",
      "size": 16777216,
      "crc32": "34458fcd",
      "md5": "bb385a5dec5734ff32d8c76027b3f632",
      "sha1": "1fdd5f9c4ba3442919f52a45b7d2303165ca6c61"
    }
  ],
  "media": [
    {
      "kind": "boxart",
      "url": "https://raw.githubusercontent.com/libretro-thumbnails/Nintendo_-_Nintendo_DS/master/Named_Boxarts/What%27s%20Cooking%20-%20Jamie%20Oliver%20%28USA%29%20%28En%2CFr%2CEs%29.png",
      "source": "libretro_thumbnails",
      "region": "us"
    },
    {
      "kind": "titlescreen",
      "url": "https://raw.githubusercontent.com/libretro-thumbnails/Nintendo_-_Nintendo_DS/master/Named_Titles/What%27s%20Cooking%20-%20Jamie%20Oliver%20%28USA%29%20%28En%2CFr%2CEs%29.png",
      "source": "libretro_thumbnails",
      "region": "us"
    },
    {
      "kind": "screenshot",
      "url": "https://raw.githubusercontent.com/libretro-thumbnails/Nintendo_-_Nintendo_DS/master/Named_Snaps/What%27s%20Cooking%20-%20Jamie%20Oliver%20%28USA%29%20%28En%2CFr%2CEs%29.png",
      "source": "libretro_thumbnails",
      "region": "us"
    },
    {
      "kind": "boxart",
      "url": "https://raw.githubusercontent.com/libretro-thumbnails/Nintendo_-_Nintendo_DS/master/Named_Boxarts/What%27s%20Cooking%20-%20Jamie%20Oliver%20%28Europe%29%20%28En%2CFr%2CDe%2CEs%2CIt%29.png",
      "source": "libretro_thumbnails",
      "region": "eu"
    },
    {
      "kind": "titlescreen",
      "url": "https://raw.githubusercontent.com/libretro-thumbnails/Nintendo_-_Nintendo_DS/master/Named_Titles/What%27s%20Cooking%20-%20Jamie%20Oliver%20%28Europe%29%20%28En%2CFr%2CDe%2CEs%2CIt%29.png",
      "source": "libretro_thumbnails",
      "region": "eu"
    },
    {
      "kind": "screenshot",
      "url": "https://raw.githubusercontent.com/libretro-thumbnails/Nintendo_-_Nintendo_DS/master/Named_Snaps/What%27s%20Cooking%20-%20Jamie%20Oliver%20%28Europe%29%20%28En%2CFr%2CDe%2CEs%2CIt%29.png",
      "source": "libretro_thumbnails",
      "region": "eu"
    }
  ]
}
