{
  "id": "goukaku-boy-series-eijukugo-target-1000",
  "platform": "gb",
  "category": "main_game",
  "titles": [
    {
      "text": "Goukaku Boy Series - Eijukugo Target 1000",
      "lang": "en",
      "script": "Latn",
      "form": "official",
      "source": "no_intro",
      "verified": false,
      "region": "jp"
    },
    {
      "text": "合格ボーイシリーズ 英熟語ターゲット1000",
      "lang": "ja",
      "script": "Jpan",
      "region": "jp",
      "form": "official",
      "source": "romu",
      "verified": true
    }
  ],
  "roms": [
    {
      "name": "Goukaku Boy Series - Eijukugo Target 1000 (Japan)",
      "source": "no_intro",
      "region": "jp",
      "size": 262144,
      "crc32": "ca20c594",
      "md5": "cc6419598044961237496d3af7f18d58",
      "sha1": "535fbf6988af70c4283d8101c72acb67d249bb96",
      "sha256": "f569e3e80659cdad294978d0b259015db9484a2ff00e96f34a1d9e69ed1dcc28"
    }
  ],
  "descriptions": [
    {
      "text": "英熟語学習ソフトです。",
      "lang": "ja",
      "source": "romu"
    }
  ],
  "media": [
    {
      "kind": "boxart",
      "url": "https://raw.githubusercontent.com/libretro-thumbnails/Nintendo_-_Game_Boy/master/Named_Boxarts/Goukaku%20Boy%20Series%20-%20Eijukugo%20Target%201000%20%28Japan%29.png",
      "source": "libretro_thumbnails",
      "region": "jp"
    },
    {
      "kind": "titlescreen",
      "url": "https://raw.githubusercontent.com/libretro-thumbnails/Nintendo_-_Game_Boy/master/Named_Titles/Goukaku%20Boy%20Series%20-%20Eijukugo%20Target%201000%20%28Japan%29.png",
      "source": "libretro_thumbnails",
      "region": "jp"
    },
    {
      "kind": "screenshot",
      "url": "https://raw.githubusercontent.com/libretro-thumbnails/Nintendo_-_Game_Boy/master/Named_Snaps/Goukaku%20Boy%20Series%20-%20Eijukugo%20Target%201000%20%28Japan%29.png",
      "source": "libretro_thumbnails",
      "region": "jp"
    }
  ]
}
