{
  "id": "hit-the-ice-vhl-the-official-video-hockey-league",
  "platform": "gb",
  "category": "main_game",
  "titles": [
    {
      "text": "Hit the Ice - VHL - The Official Video Hockey League",
      "lang": "en",
      "script": "Latn",
      "form": "official",
      "source": "no_intro",
      "verified": false,
      "region": "us"
    }
  ],
  "roms": [
    {
      "name": "Hit the Ice - VHL - The Official Video Hockey League (USA, Europe)",
      "source": "no_intro",
      "region": "us",
      "size": 131072,
      "crc32": "2c77f399",
      "md5": "66fc892b9682e8e2981fa83fa681ccad",
      "sha1": "f1631e0a97fd60a285feba1b2fc9082bca3be829",
      "sha256": "f6bdf9f2c4148ce7da23986524781ee844729f360ff9ef27d695ecf0886ff9e0"
    },
    {
      "name": "Hit the Ice - VHL - The Official Video Hockey League (USA, Europe) (Beta)",
      "source": "no_intro",
      "region": "us",
      "size": 131072,
      "crc32": "37627030",
      "md5": "3ab483b3042f9096582c16191b3a3448",
      "sha1": "c75a236ca74d60c1239f9e9b5beef929cfb0360e",
      "sha256": "2332c5fd90e5ae16bb24a70dbe6af1eeda0c71f54da6bb5bef008569f3041d7d"
    }
  ],
  "media": [
    {
      "kind": "boxart",
      "url": "https://raw.githubusercontent.com/libretro-thumbnails/Nintendo_-_Game_Boy/master/Named_Boxarts/Hit%20the%20Ice%20-%20VHL%20-%20The%20Official%20Video%20Hockey%20League%20%28USA%2C%20Europe%29.png",
      "source": "libretro_thumbnails",
      "region": "us"
    },
    {
      "kind": "titlescreen",
      "url": "https://raw.githubusercontent.com/libretro-thumbnails/Nintendo_-_Game_Boy/master/Named_Titles/Hit%20the%20Ice%20-%20VHL%20-%20The%20Official%20Video%20Hockey%20League%20%28USA%2C%20Europe%29.png",
      "source": "libretro_thumbnails",
      "region": "us"
    },
    {
      "kind": "screenshot",
      "url": "https://raw.githubusercontent.com/libretro-thumbnails/Nintendo_-_Game_Boy/master/Named_Snaps/Hit%20the%20Ice%20-%20VHL%20-%20The%20Official%20Video%20Hockey%20League%20%28USA%2C%20Europe%29.png",
      "source": "libretro_thumbnails",
      "region": "us"
    },
    {
      "kind": "titlescreen",
      "url": "https://raw.githubusercontent.com/libretro-thumbnails/Nintendo_-_Game_Boy/master/Named_Titles/Hit%20the%20Ice%20-%20VHL%20-%20The%20Official%20Video%20Hockey%20League%20%28USA%2C%20Europe%29%20%28Beta%29.png",
      "source": "libretro_thumbnails",
      "region": "us"
    }
  ]
}
