{
  "id": "magical-taruruuto-kun-2-raibaa-zone-panic",
  "platform": "gb",
  "category": "main_game",
  "titles": [
    {
      "text": "Magical Taruruuto-kun 2 - Raibaa Zone Panic!!",
      "lang": "en",
      "script": "Latn",
      "form": "official",
      "source": "no_intro",
      "verified": false,
      "region": "jp"
    },
    {
      "text": "まじかる☆タルるートくん2 ライバーゾーンパニック!!",
      "lang": "ja",
      "script": "Jpan",
      "region": "jp",
      "form": "official",
      "source": "romu",
      "verified": true
    }
  ],
  "roms": [
    {
      "name": "Magical Taruruuto-kun 2 - Raibaa Zone Panic!! (Japan)",
      "source": "no_intro",
      "region": "jp",
      "size": 131072,
      "crc32": "0aad5217",
      "md5": "e928d1f7dfaff38abc7937a6e092cec4",
      "sha1": "3be6c6b8cec80a0fe0f6edbbe40496f4d077c750",
      "sha256": "6135c053664b1dbe036ca3e5333226357354e3b15865b2071b3ed5dbb6935689"
    }
  ],
  "descriptions": [
    {
      "text": "「まじかる☆タルるートくん2 ライバーゾーンパニック!!」は、トムクリエイトが開発しバンダイが発売したアクションゲームで、1992年に日本でリリースされました。",
      "lang": "ja",
      "source": "romu"
    }
  ],
  "first_release_date": "1992-07-10",
  "media": [
    {
      "kind": "boxart",
      "url": "https://raw.githubusercontent.com/libretro-thumbnails/Nintendo_-_Game_Boy/master/Named_Boxarts/Magical%20Taruruuto-kun%202%20-%20Raibaa%20Zone%20Panic%21%21%20%28Japan%29.png",
      "source": "libretro_thumbnails",
      "region": "jp"
    },
    {
      "kind": "titlescreen",
      "url": "https://raw.githubusercontent.com/libretro-thumbnails/Nintendo_-_Game_Boy/master/Named_Titles/Magical%20Taruruuto-kun%202%20-%20Raibaa%20Zone%20Panic%21%21%20%28Japan%29.png",
      "source": "libretro_thumbnails",
      "region": "jp"
    },
    {
      "kind": "screenshot",
      "url": "https://raw.githubusercontent.com/libretro-thumbnails/Nintendo_-_Game_Boy/master/Named_Snaps/Magical%20Taruruuto-kun%202%20-%20Raibaa%20Zone%20Panic%21%21%20%28Japan%29.png",
      "source": "libretro_thumbnails",
      "region": "jp"
    }
  ]
}
