{
  "id": "midori-no-makibaoo",
  "platform": "gb",
  "category": "main_game",
  "titles": [
    {
      "text": "Midori no Makibaoo",
      "lang": "en",
      "script": "Latn",
      "region": "us",
      "form": "official",
      "source": "igdb",
      "verified": false
    },
    {
      "text": "みどりのマキバオー",
      "lang": "ja",
      "script": "Jpan",
      "region": "jp",
      "form": "official",
      "source": "igdb",
      "verified": false
    }
  ],
  "external_ids": {
    "igdb": 228619
  },
  "first_release_date": "1996-12-21"
}
