{
  "id": "rungrung-oz-no-mahou-tsukai-another-world",
  "platform": "ps1",
  "category": "main_game",
  "titles": [
    {
      "text": "RungRung - Oz no Mahou Tsukai - Another World",
      "lang": "en",
      "script": "Latn",
      "form": "official",
      "source": "no_intro",
      "verified": false,
      "region": "jp"
    }
  ],
  "roms": [
    {
      "name": "RungRung - Oz no Mahou Tsukai - Another World (Japan)",
      "source": "no_intro",
      "region": "jp",
      "size": 312932576,
      "crc32": "58287f35",
      "md5": "0d7d03f08495bab78a2e33210bcf89f0",
      "sha1": "db98b2dd47cdeac40ca8ed9944b63baf105bf498"
    }
  ]
}
