{
  "id": "simple-1500-series-vol-19-the-sugoroku",
  "platform": "ps1",
  "category": "main_game",
  "titles": [
    {
      "text": "Simple 1500 Series Vol. 19: The Sugoroku",
      "lang": "en",
      "script": "Latn",
      "region": "us",
      "form": "official",
      "source": "igdb",
      "verified": false
    },
    {
      "text": "Simple 1500 シリーズ Vol. 19 The すごろく",
      "lang": "ja",
      "script": "Jpan",
      "region": "jp",
      "form": "official",
      "source": "igdb",
      "verified": false
    }
  ],
  "external_ids": {
    "igdb": 203006
  },
  "first_release_date": "1999-11-18"
}
