{
  "id": "kanji-boy",
  "platform": "gbc",
  "category": "main_game",
  "titles": [
    {
      "text": "Kanji Boy",
      "lang": "en",
      "script": "Latn",
      "form": "official",
      "source": "no_intro",
      "verified": false,
      "region": "jp"
    },
    {
      "text": "漢字ボーイ",
      "lang": "ja",
      "script": "Jpan",
      "region": "jp",
      "form": "official",
      "source": "romu",
      "verified": true
    },
    {
      "text": "漢字BOY",
      "lang": "ja",
      "script": "Jpan",
      "region": "jp",
      "form": "official",
      "source": "skyscraper_ja",
      "verified": true
    },
    {
      "text": "漢字",
      "lang": "ja",
      "script": "Jpan",
      "region": "jp",
      "form": "official",
      "source": "gamelist_ja",
      "verified": true
    },
    {
      "text": "漢字 Boy",
      "lang": "ja",
      "script": "Jpan",
      "region": "jp",
      "form": "official",
      "source": "igdb",
      "verified": true
    }
  ],
  "roms": [
    {
      "name": "Kanji Boy (Japan) (SGB Enhanced) (GB Compatible)",
      "source": "no_intro",
      "region": "jp",
      "size": 4194304,
      "crc32": "18caa513",
      "md5": "53a98fbfddc370edd2de8eb0af5aa7ac",
      "sha1": "3876d5f64113e5365b42d30945f51f40b1d22d47"
    }
  ],
  "external_ids": {
    "igdb": 228573
  },
  "descriptions": [
    {
      "text": "日本漢字能力検定協会が監修した漢字の問題集で、過去の漢字検定2級から7級までの問題が含まれています。クイズ形式で問題に答えることで、自分の実力を評価することができます。",
      "lang": "ja",
      "source": "romu"
    }
  ],
  "first_release_date": "1999-06-03",
  "media": [
    {
      "kind": "boxart",
      "url": "https://raw.githubusercontent.com/libretro-thumbnails/Nintendo_-_Game_Boy_Color/master/Named_Boxarts/Kanji%20Boy%20%28Japan%29%20%28SGB%20Enhanced%29%20%28GB%20Compatible%29.png",
      "source": "libretro_thumbnails",
      "region": "jp"
    },
    {
      "kind": "titlescreen",
      "url": "https://raw.githubusercontent.com/libretro-thumbnails/Nintendo_-_Game_Boy_Color/master/Named_Titles/Kanji%20Boy%20%28Japan%29%20%28SGB%20Enhanced%29%20%28GB%20Compatible%29.png",
      "source": "libretro_thumbnails",
      "region": "jp"
    },
    {
      "kind": "screenshot",
      "url": "https://raw.githubusercontent.com/libretro-thumbnails/Nintendo_-_Game_Boy_Color/master/Named_Snaps/Kanji%20Boy%20%28Japan%29%20%28SGB%20Enhanced%29%20%28GB%20Compatible%29.png",
      "source": "libretro_thumbnails",
      "region": "jp"
    }
  ]
}
